MANIFEST.in
README.md
requirements.txt
setup.py
./pwsgi/__init__.py
./pwsgi/main.py
./pwsgi/router.py
./pwsgi/wrapper.py
pwsgi.egg-info/PKG-INFO
pwsgi.egg-info/SOURCES.txt
pwsgi.egg-info/dependency_links.txt
pwsgi.egg-info/entry_points.txt
pwsgi.egg-info/top_level.txt