Metadata-Version: 1.1
Name: pwsgi
Version: 0.1.11
Summary: pWSGI is a async wsgi implentation based on pulsar wsgi
Home-page: UNKNOWN
Author: ryankung
Author-email: ryankung@ieee.org
License: MIT
Platform: any
Classifier: Intended Audience :: Developers
Classifier: Programming Language :: Python
Classifier: Topic :: Software Development :: Libraries :: Python Modules
